{
    "settings": [],
    "arguments": [
        {
            "default": "P.Nothing",
            "computed": false,
            "required": false,
            "help": [
                "Account alias override"
            ],
            "forceNew": false,
            "encoder": "TF.assign \"account\" <$>",
            "name": "account",
            "method": "account",
            "conflicts": [],
            "type": "P.Maybe P.Text",
            "class": "HasAccount",
            "optional": true,
            "label": "_account"
        },
        {
            "default": "_password",
            "computed": false,
            "required": true,
            "help": [
                "Your CLC password"
            ],
            "forceNew": false,
            "encoder": "P.Just $ TF.assign \"password\"",
            "name": "password",
            "method": "password",
            "conflicts": [],
            "type": "P.Text",
            "class": "HasPassword",
            "optional": false,
            "label": "_password"
        },
        {
            "default": "_username",
            "computed": false,
            "required": true,
            "help": [
                "Your CLC username"
            ],
            "forceNew": false,
            "encoder": "P.Just $ TF.assign \"username\"",
            "name": "username",
            "method": "username",
            "conflicts": [],
            "type": "P.Text",
            "class": "HasUsername",
            "optional": false,
            "label": "_username"
        }
    ],
    "dataSources": [],
    "resources": [
        {
            "arguments": [
                {
                    "default": "TF.Nil",
                    "computed": false,
                    "required": false,
                    "help": [],
                    "forceNew": false,
                    "encoder": "TF.assign \"custom_fields\" <$> TF.attribute",
                    "name": "custom_fields",
                    "method": "customFields",
                    "conflicts": [],
                    "type": "TF.Attr s [TF.Attr s (P.HashMap P.Text (TF.Attr s P.Text))]",
                    "class": "HasCustomFields",
                    "optional": true,
                    "label": "_customFields"
                },
                {
                    "default": "TF.Nil",
                    "computed": false,
                    "required": false,
                    "help": [],
                    "forceNew": false,
                    "encoder": "TF.assign \"description\" <$> TF.attribute",
                    "name": "description",
                    "method": "description",
                    "conflicts": [],
                    "type": "TF.Attr s P.Text",
                    "class": "HasDescription",
                    "optional": true,
                    "label": "_description"
                },
                {
                    "default": "_locationId",
                    "computed": false,
                    "required": true,
                    "help": [],
                    "forceNew": false,
                    "encoder": "TF.assign \"location_id\" <$> TF.attribute",
                    "name": "location_id",
                    "method": "locationId",
                    "conflicts": [],
                    "type": "TF.Attr s P.Text",
                    "class": "HasLocationId",
                    "optional": false,
                    "label": "_locationId"
                },
                {
                    "default": "_name",
                    "computed": false,
                    "required": true,
                    "help": [],
                    "forceNew": false,
                    "encoder": "TF.assign \"name\" <$> TF.attribute",
                    "name": "name",
                    "method": "name",
                    "conflicts": [],
                    "type": "TF.Attr s P.Text",
                    "class": "HasName",
                    "optional": false,
                    "label": "_name"
                },
                {
                    "default": "_parent",
                    "computed": false,
                    "required": true,
                    "help": [],
                    "forceNew": false,
                    "encoder": "TF.assign \"parent\" <$> TF.attribute",
                    "name": "parent",
                    "method": "parent",
                    "conflicts": [],
                    "type": "TF.Attr s P.Text",
                    "class": "HasParent",
                    "optional": false,
                    "label": "_parent"
                }
            ],
            "schema": "Resource",
            "name": "GroupResource",
            "attributes": [
                {
                    "default": "TF.Nil",
                    "computed": true,
                    "required": false,
                    "help": [],
                    "forceNew": false,
                    "encoder": "TF.assign \"parent_group_id\" <$> TF.attribute",
                    "name": "parent_group_id",
                    "method": "computedParentGroupId",
                    "conflicts": [],
                    "type": "TF.Attr s P.Text",
                    "class": "HasComputedParentGroupId",
                    "optional": false,
                    "label": "_computedParentGroupId"
                }
            ],
            "parameters": [
                {
                    "default": "_locationId",
                    "computed": false,
                    "required": true,
                    "help": [],
                    "forceNew": false,
                    "encoder": "TF.assign \"location_id\" <$> TF.attribute",
                    "name": "location_id",
                    "method": "locationId",
                    "conflicts": [],
                    "type": "TF.Attr s P.Text",
                    "class": "HasLocationId",
                    "optional": false,
                    "label": "_locationId"
                },
                {
                    "default": "_name",
                    "computed": false,
                    "required": true,
                    "help": [],
                    "forceNew": false,
                    "encoder": "TF.assign \"name\" <$> TF.attribute",
                    "name": "name",
                    "method": "name",
                    "conflicts": [],
                    "type": "TF.Attr s P.Text",
                    "class": "HasName",
                    "optional": false,
                    "label": "_name"
                },
                {
                    "default": "_parent",
                    "computed": false,
                    "required": true,
                    "help": [],
                    "forceNew": false,
                    "encoder": "TF.assign \"parent\" <$> TF.attribute",
                    "name": "parent",
                    "method": "parent",
                    "conflicts": [],
                    "type": "TF.Attr s P.Text",
                    "class": "HasParent",
                    "optional": false,
                    "label": "_parent"
                }
            ],
            "type": "GroupResource s",
            "original": "clc_group"
        },
        {
            "arguments": [
                {
                    "default": "_dataCenter",
                    "computed": false,
                    "required": true,
                    "help": [],
                    "forceNew": false,
                    "encoder": "TF.assign \"data_center\" <$> TF.attribute",
                    "name": "data_center",
                    "method": "dataCenter",
                    "conflicts": [],
                    "type": "TF.Attr s P.Text",
                    "class": "HasDataCenter",
                    "optional": false,
                    "label": "_dataCenter"
                },
                {
                    "default": "_description",
                    "computed": false,
                    "required": true,
                    "help": [],
                    "forceNew": false,
                    "encoder": "TF.assign \"description\" <$> TF.attribute",
                    "name": "description",
                    "method": "description",
                    "conflicts": [],
                    "type": "TF.Attr s P.Text",
                    "class": "HasDescription",
                    "optional": false,
                    "label": "_description"
                },
                {
                    "default": "_name",
                    "computed": false,
                    "required": true,
                    "help": [],
                    "forceNew": false,
                    "encoder": "TF.assign \"name\" <$> TF.attribute",
                    "name": "name",
                    "method": "name",
                    "conflicts": [],
                    "type": "TF.Attr s P.Text",
                    "class": "HasName",
                    "optional": false,
                    "label": "_name"
                },
                {
                    "default": "TF.value \"enabled\"",
                    "computed": false,
                    "required": false,
                    "help": [],
                    "forceNew": false,
                    "encoder": "TF.assign \"status\" <$> TF.attribute",
                    "name": "status",
                    "method": "status",
                    "conflicts": [],
                    "type": "TF.Attr s P.Text",
                    "class": "HasStatus",
                    "optional": true,
                    "label": "_status"
                }
            ],
            "schema": "Resource",
            "name": "LoadBalancerResource",
            "attributes": [
                {
                    "default": "TF.Nil",
                    "computed": true,
                    "required": false,
                    "help": [],
                    "forceNew": false,
                    "encoder": "TF.assign \"ip_address\" <$> TF.attribute",
                    "name": "ip_address",
                    "method": "computedIpAddress",
                    "conflicts": [],
                    "type": "TF.Attr s P.Text",
                    "class": "HasComputedIpAddress",
                    "optional": false,
                    "label": "_computedIpAddress"
                }
            ],
            "parameters": [
                {
                    "default": "_dataCenter",
                    "computed": false,
                    "required": true,
                    "help": [],
                    "forceNew": false,
                    "encoder": "TF.assign \"data_center\" <$> TF.attribute",
                    "name": "data_center",
                    "method": "dataCenter",
                    "conflicts": [],
                    "type": "TF.Attr s P.Text",
                    "class": "HasDataCenter",
                    "optional": false,
                    "label": "_dataCenter"
                },
                {
                    "default": "_description",
                    "computed": false,
                    "required": true,
                    "help": [],
                    "forceNew": false,
                    "encoder": "TF.assign \"description\" <$> TF.attribute",
                    "name": "description",
                    "method": "description",
                    "conflicts": [],
                    "type": "TF.Attr s P.Text",
                    "class": "HasDescription",
                    "optional": false,
                    "label": "_description"
                },
                {
                    "default": "_name",
                    "computed": false,
                    "required": true,
                    "help": [],
                    "forceNew": false,
                    "encoder": "TF.assign \"name\" <$> TF.attribute",
                    "name": "name",
                    "method": "name",
                    "conflicts": [],
                    "type": "TF.Attr s P.Text",
                    "class": "HasName",
                    "optional": false,
                    "label": "_name"
                }
            ],
            "type": "LoadBalancerResource s",
            "original": "clc_load_balancer"
        },
        {
            "arguments": [
                {
                    "default": "_dataCenter",
                    "computed": false,
                    "required": true,
                    "help": [],
                    "forceNew": false,
                    "encoder": "TF.assign \"data_center\" <$> TF.attribute",
                    "name": "data_center",
                    "method": "dataCenter",
                    "conflicts": [],
                    "type": "TF.Attr s P.Text",
                    "class": "HasDataCenter",
                    "optional": false,
                    "label": "_dataCenter"
                },
                {
                    "default": "_loadBalancer",
                    "computed": false,
                    "required": true,
                    "help": [],
                    "forceNew": false,
                    "encoder": "TF.assign \"load_balancer\" <$> TF.attribute",
                    "name": "load_balancer",
                    "method": "loadBalancer",
                    "conflicts": [],
                    "type": "TF.Attr s P.Text",
                    "class": "HasLoadBalancer",
                    "optional": false,
                    "label": "_loadBalancer"
                },
                {
                    "default": "TF.value \"roundRobin\"",
                    "computed": false,
                    "required": false,
                    "help": [],
                    "forceNew": false,
                    "encoder": "TF.assign \"method\" <$> TF.attribute",
                    "name": "method",
                    "method": "method",
                    "conflicts": [],
                    "type": "TF.Attr s P.Text",
                    "class": "HasMethod",
                    "optional": true,
                    "label": "_method"
                },
                {
                    "default": "_nodes",
                    "computed": false,
                    "required": true,
                    "help": [],
                    "forceNew": false,
                    "encoder": "TF.assign \"nodes\" <$> TF.attribute",
                    "name": "nodes",
                    "method": "nodes",
                    "conflicts": [],
                    "type": "TF.Attr s [TF.Attr s (P.HashMap P.Text (TF.Attr s P.Text))]",
                    "class": "HasNodes",
                    "optional": false,
                    "label": "_nodes"
                },
                {
                    "default": "TF.value \"standard\"",
                    "computed": false,
                    "required": false,
                    "help": [],
                    "forceNew": false,
                    "encoder": "TF.assign \"persistence\" <$> TF.attribute",
                    "name": "persistence",
                    "method": "persistence",
                    "conflicts": [],
                    "type": "TF.Attr s P.Text",
                    "class": "HasPersistence",
                    "optional": true,
                    "label": "_persistence"
                },
                {
                    "default": "_port",
                    "computed": false,
                    "required": true,
                    "help": [],
                    "forceNew": false,
                    "encoder": "TF.assign \"port\" <$> TF.attribute",
                    "name": "port",
                    "method": "port",
                    "conflicts": [],
                    "type": "TF.Attr s P.Integer",
                    "class": "HasPort",
                    "optional": false,
                    "label": "_port"
                }
            ],
            "schema": "Resource",
            "name": "LoadBalancerPoolResource",
            "attributes": [],
            "parameters": [
                {
                    "default": "_dataCenter",
                    "computed": false,
                    "required": true,
                    "help": [],
                    "forceNew": false,
                    "encoder": "TF.assign \"data_center\" <$> TF.attribute",
                    "name": "data_center",
                    "method": "dataCenter",
                    "conflicts": [],
                    "type": "TF.Attr s P.Text",
                    "class": "HasDataCenter",
                    "optional": false,
                    "label": "_dataCenter"
                },
                {
                    "default": "_loadBalancer",
                    "computed": false,
                    "required": true,
                    "help": [],
                    "forceNew": false,
                    "encoder": "TF.assign \"load_balancer\" <$> TF.attribute",
                    "name": "load_balancer",
                    "method": "loadBalancer",
                    "conflicts": [],
                    "type": "TF.Attr s P.Text",
                    "class": "HasLoadBalancer",
                    "optional": false,
                    "label": "_loadBalancer"
                },
                {
                    "default": "_nodes",
                    "computed": false,
                    "required": true,
                    "help": [],
                    "forceNew": false,
                    "encoder": "TF.assign \"nodes\" <$> TF.attribute",
                    "name": "nodes",
                    "method": "nodes",
                    "conflicts": [],
                    "type": "TF.Attr s [TF.Attr s (P.HashMap P.Text (TF.Attr s P.Text))]",
                    "class": "HasNodes",
                    "optional": false,
                    "label": "_nodes"
                },
                {
                    "default": "_port",
                    "computed": false,
                    "required": true,
                    "help": [],
                    "forceNew": false,
                    "encoder": "TF.assign \"port\" <$> TF.attribute",
                    "name": "port",
                    "method": "port",
                    "conflicts": [],
                    "type": "TF.Attr s P.Integer",
                    "class": "HasPort",
                    "optional": false,
                    "label": "_port"
                }
            ],
            "type": "LoadBalancerPoolResource s",
            "original": "clc_load_balancer_pool"
        },
        {
            "arguments": [
                {
                    "default": "_ports",
                    "computed": false,
                    "required": true,
                    "help": [],
                    "forceNew": false,
                    "encoder": "TF.assign \"ports\" <$> TF.attribute",
                    "name": "ports",
                    "method": "ports",
                    "conflicts": [],
                    "type": "TF.Attr s [TF.Attr s (P.HashMap P.Text (TF.Attr s P.Text))]",
                    "class": "HasPorts",
                    "optional": false,
                    "label": "_ports"
                },
                {
                    "default": "_serverId",
                    "computed": false,
                    "required": true,
                    "help": [],
                    "forceNew": true,
                    "encoder": "TF.assign \"server_id\" <$> TF.attribute",
                    "name": "server_id",
                    "method": "serverId",
                    "conflicts": [],
                    "type": "TF.Attr s P.Text",
                    "class": "HasServerId",
                    "optional": false,
                    "label": "_serverId"
                },
                {
                    "default": "TF.Nil",
                    "computed": false,
                    "required": false,
                    "help": [],
                    "forceNew": false,
                    "encoder": "TF.assign \"source_restrictions\" <$> TF.attribute",
                    "name": "source_restrictions",
                    "method": "sourceRestrictions",
                    "conflicts": [],
                    "type": "TF.Attr s [TF.Attr s (P.HashMap P.Text (TF.Attr s P.Text))]",
                    "class": "HasSourceRestrictions",
                    "optional": true,
                    "label": "_sourceRestrictions"
                }
            ],
            "schema": "Resource",
            "name": "PublicIpResource",
            "attributes": [
                {
                    "default": "TF.Nil",
                    "computed": true,
                    "required": false,
                    "help": [],
                    "forceNew": false,
                    "encoder": "TF.assign \"internal_ip_address\" <$> TF.attribute",
                    "name": "internal_ip_address",
                    "method": "computedInternalIpAddress",
                    "conflicts": [],
                    "type": "TF.Attr s P.Text",
                    "class": "HasComputedInternalIpAddress",
                    "optional": true,
                    "label": "_computedInternalIpAddress"
                }
            ],
            "parameters": [
                {
                    "default": "_ports",
                    "computed": false,
                    "required": true,
                    "help": [],
                    "forceNew": false,
                    "encoder": "TF.assign \"ports\" <$> TF.attribute",
                    "name": "ports",
                    "method": "ports",
                    "conflicts": [],
                    "type": "TF.Attr s [TF.Attr s (P.HashMap P.Text (TF.Attr s P.Text))]",
                    "class": "HasPorts",
                    "optional": false,
                    "label": "_ports"
                },
                {
                    "default": "_serverId",
                    "computed": false,
                    "required": true,
                    "help": [],
                    "forceNew": true,
                    "encoder": "TF.assign \"server_id\" <$> TF.attribute",
                    "name": "server_id",
                    "method": "serverId",
                    "conflicts": [],
                    "type": "TF.Attr s P.Text",
                    "class": "HasServerId",
                    "optional": false,
                    "label": "_serverId"
                }
            ],
            "type": "PublicIpResource s",
            "original": "clc_public_ip"
        },
        {
            "arguments": [
                {
                    "default": "TF.Nil",
                    "computed": false,
                    "required": false,
                    "help": [],
                    "forceNew": false,
                    "encoder": "TF.assign \"aa_policy_id\" <$> TF.attribute",
                    "name": "aa_policy_id",
                    "method": "aaPolicyId",
                    "conflicts": [],
                    "type": "TF.Attr s P.Text",
                    "class": "HasAaPolicyId",
                    "optional": true,
                    "label": "_aaPolicyId"
                },
                {
                    "default": "TF.Nil",
                    "computed": false,
                    "required": false,
                    "help": [],
                    "forceNew": false,
                    "encoder": "TF.assign \"additional_disks\" <$> TF.attribute",
                    "name": "additional_disks",
                    "method": "additionalDisks",
                    "conflicts": [],
                    "type": "TF.Attr s [TF.Attr s (P.HashMap P.Text (TF.Attr s P.Text))]",
                    "class": "HasAdditionalDisks",
                    "optional": true,
                    "label": "_additionalDisks"
                },
                {
                    "default": "TF.Nil",
                    "computed": false,
                    "required": false,
                    "help": [],
                    "forceNew": true,
                    "encoder": "TF.assign \"configuration_id\" <$> TF.attribute",
                    "name": "configuration_id",
                    "method": "configurationId",
                    "conflicts": [],
                    "type": "TF.Attr s P.Text",
                    "class": "HasConfigurationId",
                    "optional": true,
                    "label": "_configurationId"
                },
                {
                    "default": "_cpu",
                    "computed": false,
                    "required": true,
                    "help": [],
                    "forceNew": false,
                    "encoder": "TF.assign \"cpu\" <$> TF.attribute",
                    "name": "cpu",
                    "method": "cpu",
                    "conflicts": [],
                    "type": "TF.Attr s P.Integer",
                    "class": "HasCpu",
                    "optional": false,
                    "label": "_cpu"
                },
                {
                    "default": "TF.Nil",
                    "computed": false,
                    "required": false,
                    "help": [],
                    "forceNew": false,
                    "encoder": "TF.assign \"custom_fields\" <$> TF.attribute",
                    "name": "custom_fields",
                    "method": "customFields",
                    "conflicts": [],
                    "type": "TF.Attr s [TF.Attr s (P.HashMap P.Text (TF.Attr s P.Text))]",
                    "class": "HasCustomFields",
                    "optional": true,
                    "label": "_customFields"
                },
                {
                    "default": "TF.Nil",
                    "computed": false,
                    "required": false,
                    "help": [],
                    "forceNew": false,
                    "encoder": "TF.assign \"description\" <$> TF.attribute",
                    "name": "description",
                    "method": "description",
                    "conflicts": [],
                    "type": "TF.Attr s P.Text",
                    "class": "HasDescription",
                    "optional": true,
                    "label": "_description"
                },
                {
                    "default": "_groupId",
                    "computed": false,
                    "required": true,
                    "help": [],
                    "forceNew": false,
                    "encoder": "TF.assign \"group_id\" <$> TF.attribute",
                    "name": "group_id",
                    "method": "groupId",
                    "conflicts": [],
                    "type": "TF.Attr s P.Text",
                    "class": "HasGroupId",
                    "optional": false,
                    "label": "_groupId"
                },
                {
                    "default": "_memoryMb",
                    "computed": false,
                    "required": true,
                    "help": [],
                    "forceNew": false,
                    "encoder": "TF.assign \"memory_mb\" <$> TF.attribute",
                    "name": "memory_mb",
                    "method": "memoryMb",
                    "conflicts": [],
                    "type": "TF.Attr s P.Integer",
                    "class": "HasMemoryMb",
                    "optional": false,
                    "label": "_memoryMb"
                },
                {
                    "default": "TF.Nil",
                    "computed": false,
                    "required": false,
                    "help": [],
                    "forceNew": false,
                    "encoder": "TF.assign \"metadata\" <$> TF.attribute",
                    "name": "metadata",
                    "method": "metadata",
                    "conflicts": [],
                    "type": "TF.Attr s (P.HashMap P.Text (TF.Attr s P.Text))",
                    "class": "HasMetadata",
                    "optional": true,
                    "label": "_metadata"
                },
                {
                    "default": "_nameTemplate",
                    "computed": false,
                    "required": true,
                    "help": [],
                    "forceNew": false,
                    "encoder": "TF.assign \"name_template\" <$> TF.attribute",
                    "name": "name_template",
                    "method": "nameTemplate",
                    "conflicts": [],
                    "type": "TF.Attr s P.Text",
                    "class": "HasNameTemplate",
                    "optional": false,
                    "label": "_nameTemplate"
                },
                {
                    "default": "TF.Nil",
                    "computed": false,
                    "required": false,
                    "help": [],
                    "forceNew": false,
                    "encoder": "TF.assign \"network_id\" <$> TF.attribute",
                    "name": "network_id",
                    "method": "networkId",
                    "conflicts": [],
                    "type": "TF.Attr s P.Text",
                    "class": "HasNetworkId",
                    "optional": true,
                    "label": "_networkId"
                },
                {
                    "default": "TF.Nil",
                    "computed": false,
                    "required": false,
                    "help": [],
                    "forceNew": true,
                    "encoder": "TF.assign \"os_type\" <$> TF.attribute",
                    "name": "os_type",
                    "method": "osType",
                    "conflicts": [],
                    "type": "TF.Attr s P.Text",
                    "class": "HasOsType",
                    "optional": true,
                    "label": "_osType"
                },
                {
                    "default": "TF.Nil",
                    "computed": false,
                    "required": false,
                    "help": [],
                    "forceNew": false,
                    "encoder": "TF.assign \"packages\" <$> TF.attribute",
                    "name": "packages",
                    "method": "packages",
                    "conflicts": [],
                    "type": "TF.Attr s [TF.Attr s (P.HashMap P.Text (TF.Attr s P.Text))]",
                    "class": "HasPackages",
                    "optional": true,
                    "label": "_packages"
                },
                {
                    "default": "_sourceServerId",
                    "computed": false,
                    "required": true,
                    "help": [],
                    "forceNew": true,
                    "encoder": "TF.assign \"source_server_id\" <$> TF.attribute",
                    "name": "source_server_id",
                    "method": "sourceServerId",
                    "conflicts": [],
                    "type": "TF.Attr s P.Text",
                    "class": "HasSourceServerId",
                    "optional": false,
                    "label": "_sourceServerId"
                },
                {
                    "default": "TF.value \"standard\"",
                    "computed": false,
                    "required": false,
                    "help": [],
                    "forceNew": false,
                    "encoder": "TF.assign \"storage_type\" <$> TF.attribute",
                    "name": "storage_type",
                    "method": "storageType",
                    "conflicts": [],
                    "type": "TF.Attr s P.Text",
                    "class": "HasStorageType",
                    "optional": true,
                    "label": "_storageType"
                },
                {
                    "default": "TF.value \"standard\"",
                    "computed": false,
                    "required": false,
                    "help": [],
                    "forceNew": true,
                    "encoder": "TF.assign \"type\" <$> TF.attribute",
                    "name": "type",
                    "method": "type'",
                    "conflicts": [],
                    "type": "TF.Attr s P.Text",
                    "class": "HasType'",
                    "optional": true,
                    "label": "_type'"
                }
            ],
            "schema": "Resource",
            "name": "ServerResource",
            "attributes": [
                {
                    "default": "TF.Nil",
                    "computed": true,
                    "required": false,
                    "help": [],
                    "forceNew": false,
                    "encoder": "TF.assign \"created_date\" <$> TF.attribute",
                    "name": "created_date",
                    "method": "computedCreatedDate",
                    "conflicts": [],
                    "type": "TF.Attr s P.Text",
                    "class": "HasComputedCreatedDate",
                    "optional": false,
                    "label": "_computedCreatedDate"
                },
                {
                    "default": "TF.Nil",
                    "computed": true,
                    "required": false,
                    "help": [],
                    "forceNew": false,
                    "encoder": "TF.assign \"modified_date\" <$> TF.attribute",
                    "name": "modified_date",
                    "method": "computedModifiedDate",
                    "conflicts": [],
                    "type": "TF.Attr s P.Text",
                    "class": "HasComputedModifiedDate",
                    "optional": false,
                    "label": "_computedModifiedDate"
                },
                {
                    "default": "TF.Nil",
                    "computed": true,
                    "required": false,
                    "help": [],
                    "forceNew": false,
                    "encoder": "TF.assign \"name\" <$> TF.attribute",
                    "name": "name",
                    "method": "computedName",
                    "conflicts": [],
                    "type": "TF.Attr s P.Text",
                    "class": "HasComputedName",
                    "optional": false,
                    "label": "_computedName"
                },
                {
                    "default": "TF.Nil",
                    "computed": true,
                    "required": false,
                    "help": [],
                    "forceNew": false,
                    "encoder": "TF.assign \"password\" <$> TF.attribute",
                    "name": "password",
                    "method": "computedPassword",
                    "conflicts": [],
                    "type": "TF.Attr s P.Text",
                    "class": "HasComputedPassword",
                    "optional": true,
                    "label": "_computedPassword"
                },
                {
                    "default": "TF.Nil",
                    "computed": true,
                    "required": false,
                    "help": [],
                    "forceNew": false,
                    "encoder": "TF.assign \"power_state\" <$> TF.attribute",
                    "name": "power_state",
                    "method": "computedPowerState",
                    "conflicts": [],
                    "type": "TF.Attr s P.Text",
                    "class": "HasComputedPowerState",
                    "optional": true,
                    "label": "_computedPowerState"
                },
                {
                    "default": "TF.Nil",
                    "computed": true,
                    "required": false,
                    "help": [],
                    "forceNew": false,
                    "encoder": "TF.assign \"private_ip_address\" <$> TF.attribute",
                    "name": "private_ip_address",
                    "method": "computedPrivateIpAddress",
                    "conflicts": [],
                    "type": "TF.Attr s P.Text",
                    "class": "HasComputedPrivateIpAddress",
                    "optional": true,
                    "label": "_computedPrivateIpAddress"
                },
                {
                    "default": "TF.Nil",
                    "computed": true,
                    "required": false,
                    "help": [],
                    "forceNew": false,
                    "encoder": "TF.assign \"public_ip_address\" <$> TF.attribute",
                    "name": "public_ip_address",
                    "method": "computedPublicIpAddress",
                    "conflicts": [],
                    "type": "TF.Attr s P.Text",
                    "class": "HasComputedPublicIpAddress",
                    "optional": false,
                    "label": "_computedPublicIpAddress"
                }
            ],
            "parameters": [
                {
                    "default": "_cpu",
                    "computed": false,
                    "required": true,
                    "help": [],
                    "forceNew": false,
                    "encoder": "TF.assign \"cpu\" <$> TF.attribute",
                    "name": "cpu",
                    "method": "cpu",
                    "conflicts": [],
                    "type": "TF.Attr s P.Integer",
                    "class": "HasCpu",
                    "optional": false,
                    "label": "_cpu"
                },
                {
                    "default": "_groupId",
                    "computed": false,
                    "required": true,
                    "help": [],
                    "forceNew": false,
                    "encoder": "TF.assign \"group_id\" <$> TF.attribute",
                    "name": "group_id",
                    "method": "groupId",
                    "conflicts": [],
                    "type": "TF.Attr s P.Text",
                    "class": "HasGroupId",
                    "optional": false,
                    "label": "_groupId"
                },
                {
                    "default": "_memoryMb",
                    "computed": false,
                    "required": true,
                    "help": [],
                    "forceNew": false,
                    "encoder": "TF.assign \"memory_mb\" <$> TF.attribute",
                    "name": "memory_mb",
                    "method": "memoryMb",
                    "conflicts": [],
                    "type": "TF.Attr s P.Integer",
                    "class": "HasMemoryMb",
                    "optional": false,
                    "label": "_memoryMb"
                },
                {
                    "default": "_nameTemplate",
                    "computed": false,
                    "required": true,
                    "help": [],
                    "forceNew": false,
                    "encoder": "TF.assign \"name_template\" <$> TF.attribute",
                    "name": "name_template",
                    "method": "nameTemplate",
                    "conflicts": [],
                    "type": "TF.Attr s P.Text",
                    "class": "HasNameTemplate",
                    "optional": false,
                    "label": "_nameTemplate"
                },
                {
                    "default": "_sourceServerId",
                    "computed": false,
                    "required": true,
                    "help": [],
                    "forceNew": true,
                    "encoder": "TF.assign \"source_server_id\" <$> TF.attribute",
                    "name": "source_server_id",
                    "method": "sourceServerId",
                    "conflicts": [],
                    "type": "TF.Attr s P.Text",
                    "class": "HasSourceServerId",
                    "optional": false,
                    "label": "_sourceServerId"
                }
            ],
            "type": "ServerResource s",
            "original": "clc_server"
        }
    ],
    "dependencies": [
        "base",
        "unordered-containers",
        "text",
        "terrafomo",
        "hashable",
        "microlens"
    ],
    "name": "CenturyLinkCloud",
    "parameters": [
        {
            "default": "_password",
            "computed": false,
            "required": true,
            "help": [
                "Your CLC password"
            ],
            "forceNew": false,
            "encoder": "P.Just $ TF.assign \"password\"",
            "name": "password",
            "method": "password",
            "conflicts": [],
            "type": "P.Text",
            "class": "HasPassword",
            "optional": false,
            "label": "_password"
        },
        {
            "default": "_username",
            "computed": false,
            "required": true,
            "help": [
                "Your CLC username"
            ],
            "forceNew": false,
            "encoder": "P.Just $ TF.assign \"username\"",
            "name": "username",
            "method": "username",
            "conflicts": [],
            "type": "P.Text",
            "class": "HasUsername",
            "optional": false,
            "label": "_username"
        }
    ],
    "package": "terrafomo-centurylinkcloud",
    "type": "Provider",
    "original": "clc"
}