{
    "settings": [
        {
            "arguments": [
                {
                    "default": "_action",
                    "computed": false,
                    "required": true,
                    "help": [],
                    "forceNew": false,
                    "encoder": "TF.assign \"action\" <$> TF.attribute",
                    "name": "action",
                    "method": "action",
                    "conflicts": [],
                    "type": "TF.Attr s P.Text",
                    "class": "HasAction",
                    "optional": false,
                    "label": "_action"
                },
                {
                    "default": "_source",
                    "computed": false,
                    "required": true,
                    "help": [],
                    "forceNew": false,
                    "encoder": "TF.assign \"source\" <$> TF.attribute",
                    "name": "source",
                    "method": "source",
                    "conflicts": [],
                    "type": "TF.Attr s P.Text",
                    "class": "HasSource",
                    "optional": false,
                    "label": "_source"
                }
            ],
            "name": "Rule",
            "attributes": [],
            "parameters": [
                {
                    "default": "_action",
                    "computed": false,
                    "required": true,
                    "help": [],
                    "forceNew": false,
                    "encoder": "TF.assign \"action\" <$> TF.attribute",
                    "name": "action",
                    "method": "action",
                    "conflicts": [],
                    "type": "TF.Attr s P.Text",
                    "class": "HasAction",
                    "optional": false,
                    "label": "_action"
                },
                {
                    "default": "_source",
                    "computed": false,
                    "required": true,
                    "help": [],
                    "forceNew": false,
                    "encoder": "TF.assign \"source\" <$> TF.attribute",
                    "name": "source",
                    "method": "source",
                    "conflicts": [],
                    "type": "TF.Attr s P.Text",
                    "class": "HasSource",
                    "optional": false,
                    "label": "_source"
                }
            ],
            "hashable": false,
            "type": "Rule s",
            "original": "rule"
        },
        {
            "arguments": [],
            "name": "Organization",
            "attributes": [
                {
                    "default": "TF.Nil",
                    "computed": true,
                    "required": false,
                    "help": [],
                    "forceNew": false,
                    "encoder": "TF.assign \"locked\" <$> TF.attribute",
                    "name": "locked",
                    "method": "computedLocked",
                    "conflicts": [],
                    "type": "TF.Attr s P.Bool",
                    "class": "HasComputedLocked",
                    "optional": false,
                    "label": "_computedLocked"
                },
                {
                    "default": "TF.Nil",
                    "computed": true,
                    "required": false,
                    "help": [],
                    "forceNew": false,
                    "encoder": "TF.assign \"name\" <$> TF.attribute",
                    "name": "name",
                    "method": "computedName",
                    "conflicts": [],
                    "type": "TF.Attr s P.Text",
                    "class": "HasComputedName",
                    "optional": false,
                    "label": "_computedName"
                },
                {
                    "default": "TF.Nil",
                    "computed": true,
                    "required": false,
                    "help": [],
                    "forceNew": false,
                    "encoder": "TF.assign \"personal\" <$> TF.attribute",
                    "name": "personal",
                    "method": "computedPersonal",
                    "conflicts": [],
                    "type": "TF.Attr s P.Bool",
                    "class": "HasComputedPersonal",
                    "optional": false,
                    "label": "_computedPersonal"
                }
            ],
            "parameters": [],
            "hashable": false,
            "type": "Organization s",
            "original": "organization"
        },
        {
            "arguments": [],
            "name": "Tunnels",
            "attributes": [
                {
                    "default": "TF.Nil",
                    "computed": true,
                    "required": false,
                    "help": [],
                    "forceNew": false,
                    "encoder": "TF.assign \"ip\" <$> TF.attribute",
                    "name": "ip",
                    "method": "computedIp",
                    "conflicts": [],
                    "type": "TF.Attr s P.Text",
                    "class": "HasComputedIp",
                    "optional": true,
                    "label": "_computedIp"
                },
                {
                    "default": "TF.Nil",
                    "computed": true,
                    "required": false,
                    "help": [],
                    "forceNew": false,
                    "encoder": "TF.assign \"pre_shared_key\" <$> TF.attribute",
                    "name": "pre_shared_key",
                    "method": "computedPreSharedKey",
                    "conflicts": [],
                    "type": "TF.Attr s P.Text",
                    "class": "HasComputedPreSharedKey",
                    "optional": true,
                    "label": "_computedPreSharedKey"
                }
            ],
            "parameters": [],
            "hashable": false,
            "type": "Tunnels s",
            "original": "tunnels"
        }
    ],
    "arguments": [
        {
            "default": "P.Nothing",
            "computed": false,
            "required": false,
            "help": [],
            "forceNew": false,
            "encoder": "TF.assign \"api_key\" <$>",
            "name": "api_key",
            "method": "apiKey",
            "conflicts": [],
            "type": "P.Maybe P.Text",
            "class": "HasApiKey",
            "optional": true,
            "label": "_apiKey"
        },
        {
            "default": "P.Nothing",
            "computed": false,
            "required": false,
            "help": [],
            "forceNew": false,
            "encoder": "TF.assign \"email\" <$>",
            "name": "email",
            "method": "email",
            "conflicts": [],
            "type": "P.Maybe P.Text",
            "class": "HasEmail",
            "optional": true,
            "label": "_email"
        },
        {
            "default": "P.Nothing",
            "computed": false,
            "required": false,
            "help": [],
            "forceNew": false,
            "encoder": "TF.assign \"headers\" <$>",
            "name": "headers",
            "method": "headers",
            "conflicts": [],
            "type": "P.Maybe P.Text",
            "class": "HasHeaders",
            "optional": true,
            "label": "_headers"
        }
    ],
    "dataSources": [
        {
            "arguments": [
                {
                    "default": "_name",
                    "computed": false,
                    "required": true,
                    "help": [],
                    "forceNew": false,
                    "encoder": "TF.assign \"name\" <$> TF.attribute",
                    "name": "name",
                    "method": "name",
                    "conflicts": [],
                    "type": "TF.Attr s P.Text",
                    "class": "HasName",
                    "optional": false,
                    "label": "_name"
                }
            ],
            "schema": "DataSource",
            "name": "AppData",
            "attributes": [
                {
                    "default": "TF.Nil",
                    "computed": true,
                    "required": false,
                    "help": [],
                    "forceNew": false,
                    "encoder": "TF.assign \"acm\" <$> TF.attribute",
                    "name": "acm",
                    "method": "computedAcm",
                    "conflicts": [],
                    "type": "TF.Attr s P.Bool",
                    "class": "HasComputedAcm",
                    "optional": false,
                    "label": "_computedAcm"
                },
                {
                    "default": "TF.Nil",
                    "computed": true,
                    "required": false,
                    "help": [],
                    "forceNew": false,
                    "encoder": "TF.assign \"buildpacks\" <$> TF.attribute",
                    "name": "buildpacks",
                    "method": "computedBuildpacks",
                    "conflicts": [],
                    "type": "TF.Attr s [TF.Attr s P.Text]",
                    "class": "HasComputedBuildpacks",
                    "optional": false,
                    "label": "_computedBuildpacks"
                },
                {
                    "default": "TF.Nil",
                    "computed": true,
                    "required": false,
                    "help": [],
                    "forceNew": false,
                    "encoder": "TF.assign \"config_vars\" <$> TF.attribute",
                    "name": "config_vars",
                    "method": "computedConfigVars",
                    "conflicts": [],
                    "type": "TF.Attr s (P.HashMap P.Text (TF.Attr s P.Text))",
                    "class": "HasComputedConfigVars",
                    "optional": false,
                    "label": "_computedConfigVars"
                },
                {
                    "default": "TF.Nil",
                    "computed": true,
                    "required": false,
                    "help": [],
                    "forceNew": false,
                    "encoder": "TF.assign \"git_url\" <$> TF.attribute",
                    "name": "git_url",
                    "method": "computedGitUrl",
                    "conflicts": [],
                    "type": "TF.Attr s P.Text",
                    "class": "HasComputedGitUrl",
                    "optional": false,
                    "label": "_computedGitUrl"
                },
                {
                    "default": "TF.Nil",
                    "computed": true,
                    "required": false,
                    "help": [],
                    "forceNew": false,
                    "encoder": "TF.assign \"heroku_hostname\" <$> TF.attribute",
                    "name": "heroku_hostname",
                    "method": "computedHerokuHostname",
                    "conflicts": [],
                    "type": "TF.Attr s P.Text",
                    "class": "HasComputedHerokuHostname",
                    "optional": false,
                    "label": "_computedHerokuHostname"
                },
                {
                    "default": "TF.Nil",
                    "computed": true,
                    "required": false,
                    "help": [],
                    "forceNew": false,
                    "encoder": "TF.assign \"internal_routing\" <$> TF.attribute",
                    "name": "internal_routing",
                    "method": "computedInternalRouting",
                    "conflicts": [],
                    "type": "TF.Attr s P.Bool",
                    "class": "HasComputedInternalRouting",
                    "optional": false,
                    "label": "_computedInternalRouting"
                },
                {
                    "default": "TF.Nil",
                    "computed": true,
                    "required": false,
                    "help": [],
                    "forceNew": false,
                    "encoder": "TF.assign \"organization\" <$> TF.attribute",
                    "name": "organization",
                    "method": "computedOrganization",
                    "conflicts": [],
                    "type": "TF.Attr s [Organization s]",
                    "class": "HasComputedOrganization",
                    "optional": false,
                    "label": "_computedOrganization"
                },
                {
                    "default": "TF.Nil",
                    "computed": true,
                    "required": false,
                    "help": [],
                    "forceNew": false,
                    "encoder": "TF.assign \"region\" <$> TF.attribute",
                    "name": "region",
                    "method": "computedRegion",
                    "conflicts": [],
                    "type": "TF.Attr s P.Text",
                    "class": "HasComputedRegion",
                    "optional": false,
                    "label": "_computedRegion"
                },
                {
                    "default": "TF.Nil",
                    "computed": true,
                    "required": false,
                    "help": [],
                    "forceNew": false,
                    "encoder": "TF.assign \"space\" <$> TF.attribute",
                    "name": "space",
                    "method": "computedSpace",
                    "conflicts": [],
                    "type": "TF.Attr s P.Text",
                    "class": "HasComputedSpace",
                    "optional": false,
                    "label": "_computedSpace"
                },
                {
                    "default": "TF.Nil",
                    "computed": true,
                    "required": false,
                    "help": [],
                    "forceNew": false,
                    "encoder": "TF.assign \"stack\" <$> TF.attribute",
                    "name": "stack",
                    "method": "computedStack",
                    "conflicts": [],
                    "type": "TF.Attr s P.Text",
                    "class": "HasComputedStack",
                    "optional": false,
                    "label": "_computedStack"
                },
                {
                    "default": "TF.Nil",
                    "computed": true,
                    "required": false,
                    "help": [],
                    "forceNew": false,
                    "encoder": "TF.assign \"web_url\" <$> TF.attribute",
                    "name": "web_url",
                    "method": "computedWebUrl",
                    "conflicts": [],
                    "type": "TF.Attr s P.Text",
                    "class": "HasComputedWebUrl",
                    "optional": false,
                    "label": "_computedWebUrl"
                }
            ],
            "parameters": [
                {
                    "default": "_name",
                    "computed": false,
                    "required": true,
                    "help": [],
                    "forceNew": false,
                    "encoder": "TF.assign \"name\" <$> TF.attribute",
                    "name": "name",
                    "method": "name",
                    "conflicts": [],
                    "type": "TF.Attr s P.Text",
                    "class": "HasName",
                    "optional": false,
                    "label": "_name"
                }
            ],
            "type": "AppData s",
            "original": "heroku_app"
        },
        {
            "arguments": [
                {
                    "default": "_name",
                    "computed": false,
                    "required": true,
                    "help": [],
                    "forceNew": false,
                    "encoder": "TF.assign \"name\" <$> TF.attribute",
                    "name": "name",
                    "method": "name",
                    "conflicts": [],
                    "type": "TF.Attr s P.Text",
                    "class": "HasName",
                    "optional": false,
                    "label": "_name"
                }
            ],
            "schema": "DataSource",
            "name": "SpaceData",
            "attributes": [
                {
                    "default": "TF.Nil",
                    "computed": true,
                    "required": false,
                    "help": [],
                    "forceNew": false,
                    "encoder": "TF.assign \"organization\" <$> TF.attribute",
                    "name": "organization",
                    "method": "computedOrganization",
                    "conflicts": [],
                    "type": "TF.Attr s P.Text",
                    "class": "HasComputedOrganization",
                    "optional": false,
                    "label": "_computedOrganization"
                },
                {
                    "default": "TF.Nil",
                    "computed": true,
                    "required": false,
                    "help": [],
                    "forceNew": false,
                    "encoder": "TF.assign \"outbound_ips\" <$> TF.attribute",
                    "name": "outbound_ips",
                    "method": "computedOutboundIps",
                    "conflicts": [],
                    "type": "TF.Attr s [TF.Attr s P.Text]",
                    "class": "HasComputedOutboundIps",
                    "optional": false,
                    "label": "_computedOutboundIps"
                },
                {
                    "default": "TF.Nil",
                    "computed": true,
                    "required": false,
                    "help": [],
                    "forceNew": false,
                    "encoder": "TF.assign \"region\" <$> TF.attribute",
                    "name": "region",
                    "method": "computedRegion",
                    "conflicts": [],
                    "type": "TF.Attr s P.Text",
                    "class": "HasComputedRegion",
                    "optional": false,
                    "label": "_computedRegion"
                },
                {
                    "default": "TF.Nil",
                    "computed": true,
                    "required": false,
                    "help": [],
                    "forceNew": false,
                    "encoder": "TF.assign \"shield\" <$> TF.attribute",
                    "name": "shield",
                    "method": "computedShield",
                    "conflicts": [],
                    "type": "TF.Attr s P.Bool",
                    "class": "HasComputedShield",
                    "optional": false,
                    "label": "_computedShield"
                },
                {
                    "default": "TF.Nil",
                    "computed": true,
                    "required": false,
                    "help": [],
                    "forceNew": false,
                    "encoder": "TF.assign \"state\" <$> TF.attribute",
                    "name": "state",
                    "method": "computedState",
                    "conflicts": [],
                    "type": "TF.Attr s P.Text",
                    "class": "HasComputedState",
                    "optional": false,
                    "label": "_computedState"
                },
                {
                    "default": "TF.Nil",
                    "computed": true,
                    "required": false,
                    "help": [],
                    "forceNew": false,
                    "encoder": "TF.assign \"trusted_ip_ranges\" <$> TF.attribute",
                    "name": "trusted_ip_ranges",
                    "method": "computedTrustedIpRanges",
                    "conflicts": [],
                    "type": "TF.Attr s [TF.Attr s P.Text]",
                    "class": "HasComputedTrustedIpRanges",
                    "optional": false,
                    "label": "_computedTrustedIpRanges"
                }
            ],
            "parameters": [
                {
                    "default": "_name",
                    "computed": false,
                    "required": true,
                    "help": [],
                    "forceNew": false,
                    "encoder": "TF.assign \"name\" <$> TF.attribute",
                    "name": "name",
                    "method": "name",
                    "conflicts": [],
                    "type": "TF.Attr s P.Text",
                    "class": "HasName",
                    "optional": false,
                    "label": "_name"
                }
            ],
            "type": "SpaceData s",
            "original": "heroku_space"
        },
        {
            "arguments": [
                {
                    "default": "_name",
                    "computed": false,
                    "required": true,
                    "help": [],
                    "forceNew": false,
                    "encoder": "TF.assign \"name\" <$> TF.attribute",
                    "name": "name",
                    "method": "name",
                    "conflicts": [],
                    "type": "TF.Attr s P.Text",
                    "class": "HasName",
                    "optional": false,
                    "label": "_name"
                }
            ],
            "schema": "DataSource",
            "name": "SpacePeeringInfoData",
            "attributes": [
                {
                    "default": "TF.Nil",
                    "computed": true,
                    "required": false,
                    "help": [],
                    "forceNew": false,
                    "encoder": "TF.assign \"aws_account_id\" <$> TF.attribute",
                    "name": "aws_account_id",
                    "method": "computedAwsAccountId",
                    "conflicts": [],
                    "type": "TF.Attr s P.Text",
                    "class": "HasComputedAwsAccountId",
                    "optional": false,
                    "label": "_computedAwsAccountId"
                },
                {
                    "default": "TF.Nil",
                    "computed": true,
                    "required": false,
                    "help": [],
                    "forceNew": false,
                    "encoder": "TF.assign \"aws_region\" <$> TF.attribute",
                    "name": "aws_region",
                    "method": "computedAwsRegion",
                    "conflicts": [],
                    "type": "TF.Attr s P.Text",
                    "class": "HasComputedAwsRegion",
                    "optional": false,
                    "label": "_computedAwsRegion"
                },
                {
                    "default": "TF.Nil",
                    "computed": true,
                    "required": false,
                    "help": [],
                    "forceNew": false,
                    "encoder": "TF.assign \"dyno_cidr_blocks\" <$> TF.attribute",
                    "name": "dyno_cidr_blocks",
                    "method": "computedDynoCidrBlocks",
                    "conflicts": [],
                    "type": "TF.Attr s [TF.Attr s P.Text]",
                    "class": "HasComputedDynoCidrBlocks",
                    "optional": false,
                    "label": "_computedDynoCidrBlocks"
                },
                {
                    "default": "TF.Nil",
                    "computed": true,
                    "required": false,
                    "help": [],
                    "forceNew": false,
                    "encoder": "TF.assign \"unavailable_cidr_blocks\" <$> TF.attribute",
                    "name": "unavailable_cidr_blocks",
                    "method": "computedUnavailableCidrBlocks",
                    "conflicts": [],
                    "type": "TF.Attr s [TF.Attr s P.Text]",
                    "class": "HasComputedUnavailableCidrBlocks",
                    "optional": false,
                    "label": "_computedUnavailableCidrBlocks"
                },
                {
                    "default": "TF.Nil",
                    "computed": true,
                    "required": false,
                    "help": [],
                    "forceNew": false,
                    "encoder": "TF.assign \"vpc_cidr\" <$> TF.attribute",
                    "name": "vpc_cidr",
                    "method": "computedVpcCidr",
                    "conflicts": [],
                    "type": "TF.Attr s P.Bool",
                    "class": "HasComputedVpcCidr",
                    "optional": false,
                    "label": "_computedVpcCidr"
                },
                {
                    "default": "TF.Nil",
                    "computed": true,
                    "required": false,
                    "help": [],
                    "forceNew": false,
                    "encoder": "TF.assign \"vpc_id\" <$> TF.attribute",
                    "name": "vpc_id",
                    "method": "computedVpcId",
                    "conflicts": [],
                    "type": "TF.Attr s P.Text",
                    "class": "HasComputedVpcId",
                    "optional": false,
                    "label": "_computedVpcId"
                }
            ],
            "parameters": [
                {
                    "default": "_name",
                    "computed": false,
                    "required": true,
                    "help": [],
                    "forceNew": false,
                    "encoder": "TF.assign \"name\" <$> TF.attribute",
                    "name": "name",
                    "method": "name",
                    "conflicts": [],
                    "type": "TF.Attr s P.Text",
                    "class": "HasName",
                    "optional": false,
                    "label": "_name"
                }
            ],
            "type": "SpacePeeringInfoData s",
            "original": "heroku_space_peering_info"
        }
    ],
    "resources": [
        {
            "arguments": [
                {
                    "default": "_app",
                    "computed": false,
                    "required": true,
                    "help": [],
                    "forceNew": true,
                    "encoder": "TF.assign \"app\" <$> TF.attribute",
                    "name": "app",
                    "method": "app",
                    "conflicts": [],
                    "type": "TF.Attr s P.Text",
                    "class": "HasApp",
                    "optional": false,
                    "label": "_app"
                },
                {
                    "default": "TF.Nil",
                    "computed": false,
                    "required": false,
                    "help": [],
                    "forceNew": true,
                    "encoder": "TF.assign \"config\" <$> TF.attribute",
                    "name": "config",
                    "method": "config",
                    "conflicts": [],
                    "type": "TF.Attr s [TF.Attr s (P.HashMap P.Text (TF.Attr s P.Text))]",
                    "class": "HasConfig",
                    "optional": true,
                    "label": "_config"
                },
                {
                    "default": "_plan",
                    "computed": false,
                    "required": true,
                    "help": [],
                    "forceNew": false,
                    "encoder": "TF.assign \"plan\" <$> TF.attribute",
                    "name": "plan",
                    "method": "plan",
                    "conflicts": [],
                    "type": "TF.Attr s P.Text",
                    "class": "HasPlan",
                    "optional": false,
                    "label": "_plan"
                }
            ],
            "schema": "Resource",
            "name": "AddonResource",
            "attributes": [
                {
                    "default": "TF.Nil",
                    "computed": true,
                    "required": false,
                    "help": [],
                    "forceNew": false,
                    "encoder": "TF.assign \"config_vars\" <$> TF.attribute",
                    "name": "config_vars",
                    "method": "computedConfigVars",
                    "conflicts": [],
                    "type": "TF.Attr s [TF.Attr s P.Text]",
                    "class": "HasComputedConfigVars",
                    "optional": false,
                    "label": "_computedConfigVars"
                },
                {
                    "default": "TF.Nil",
                    "computed": true,
                    "required": false,
                    "help": [],
                    "forceNew": false,
                    "encoder": "TF.assign \"name\" <$> TF.attribute",
                    "name": "name",
                    "method": "computedName",
                    "conflicts": [],
                    "type": "TF.Attr s P.Text",
                    "class": "HasComputedName",
                    "optional": false,
                    "label": "_computedName"
                },
                {
                    "default": "TF.Nil",
                    "computed": true,
                    "required": false,
                    "help": [],
                    "forceNew": false,
                    "encoder": "TF.assign \"provider_id\" <$> TF.attribute",
                    "name": "provider_id",
                    "method": "computedProviderId",
                    "conflicts": [],
                    "type": "TF.Attr s P.Text",
                    "class": "HasComputedProviderId",
                    "optional": false,
                    "label": "_computedProviderId"
                }
            ],
            "parameters": [
                {
                    "default": "_app",
                    "computed": false,
                    "required": true,
                    "help": [],
                    "forceNew": true,
                    "encoder": "TF.assign \"app\" <$> TF.attribute",
                    "name": "app",
                    "method": "app",
                    "conflicts": [],
                    "type": "TF.Attr s P.Text",
                    "class": "HasApp",
                    "optional": false,
                    "label": "_app"
                },
                {
                    "default": "_plan",
                    "computed": false,
                    "required": true,
                    "help": [],
                    "forceNew": false,
                    "encoder": "TF.assign \"plan\" <$> TF.attribute",
                    "name": "plan",
                    "method": "plan",
                    "conflicts": [],
                    "type": "TF.Attr s P.Text",
                    "class": "HasPlan",
                    "optional": false,
                    "label": "_plan"
                }
            ],
            "type": "AddonResource s",
            "original": "heroku_addon"
        },
        {
            "arguments": [
                {
                    "default": "_addonId",
                    "computed": false,
                    "required": true,
                    "help": [],
                    "forceNew": true,
                    "encoder": "TF.assign \"addon_id\" <$> TF.attribute",
                    "name": "addon_id",
                    "method": "addonId",
                    "conflicts": [],
                    "type": "TF.Attr s P.Text",
                    "class": "HasAddonId",
                    "optional": false,
                    "label": "_addonId"
                },
                {
                    "default": "_appId",
                    "computed": false,
                    "required": true,
                    "help": [],
                    "forceNew": true,
                    "encoder": "TF.assign \"app_id\" <$> TF.attribute",
                    "name": "app_id",
                    "method": "appId",
                    "conflicts": [],
                    "type": "TF.Attr s P.Text",
                    "class": "HasAppId",
                    "optional": false,
                    "label": "_appId"
                }
            ],
            "schema": "Resource",
            "name": "AddonAttachmentResource",
            "attributes": [
                {
                    "default": "TF.Nil",
                    "computed": true,
                    "required": false,
                    "help": [],
                    "forceNew": true,
                    "encoder": "TF.assign \"name\" <$> TF.attribute",
                    "name": "name",
                    "method": "computedName",
                    "conflicts": [],
                    "type": "TF.Attr s P.Text",
                    "class": "HasComputedName",
                    "optional": true,
                    "label": "_computedName"
                }
            ],
            "parameters": [
                {
                    "default": "_addonId",
                    "computed": false,
                    "required": true,
                    "help": [],
                    "forceNew": true,
                    "encoder": "TF.assign \"addon_id\" <$> TF.attribute",
                    "name": "addon_id",
                    "method": "addonId",
                    "conflicts": [],
                    "type": "TF.Attr s P.Text",
                    "class": "HasAddonId",
                    "optional": false,
                    "label": "_addonId"
                },
                {
                    "default": "_appId",
                    "computed": false,
                    "required": true,
                    "help": [],
                    "forceNew": true,
                    "encoder": "TF.assign \"app_id\" <$> TF.attribute",
                    "name": "app_id",
                    "method": "appId",
                    "conflicts": [],
                    "type": "TF.Attr s P.Text",
                    "class": "HasAppId",
                    "optional": false,
                    "label": "_appId"
                }
            ],
            "type": "AddonAttachmentResource s",
            "original": "heroku_addon_attachment"
        },
        {
            "arguments": [
                {
                    "default": "TF.Nil",
                    "computed": false,
                    "required": false,
                    "help": [],
                    "forceNew": false,
                    "encoder": "TF.assign \"acm\" <$> TF.attribute",
                    "name": "acm",
                    "method": "acm",
                    "conflicts": [],
                    "type": "TF.Attr s P.Bool",
                    "class": "HasAcm",
                    "optional": true,
                    "label": "_acm"
                },
                {
                    "default": "TF.Nil",
                    "computed": false,
                    "required": false,
                    "help": [],
                    "forceNew": false,
                    "encoder": "TF.assign \"buildpacks\" <$> TF.attribute",
                    "name": "buildpacks",
                    "method": "buildpacks",
                    "conflicts": [],
                    "type": "TF.Attr s [TF.Attr s P.Text]",
                    "class": "HasBuildpacks",
                    "optional": true,
                    "label": "_buildpacks"
                },
                {
                    "default": "_name",
                    "computed": false,
                    "required": true,
                    "help": [],
                    "forceNew": false,
                    "encoder": "TF.assign \"name\" <$> TF.attribute",
                    "name": "name",
                    "method": "name",
                    "conflicts": [],
                    "type": "TF.Attr s P.Text",
                    "class": "HasName",
                    "optional": false,
                    "label": "_name"
                },
                {
                    "default": "TF.Nil",
                    "computed": false,
                    "required": false,
                    "help": [],
                    "forceNew": true,
                    "encoder": "TF.assign \"organization\" <$> TF.attribute",
                    "name": "organization",
                    "method": "organization",
                    "conflicts": [],
                    "type": "TF.Attr s [Organization s]",
                    "class": "HasOrganization",
                    "optional": true,
                    "label": "_organization"
                },
                {
                    "default": "_region",
                    "computed": false,
                    "required": true,
                    "help": [],
                    "forceNew": true,
                    "encoder": "TF.assign \"region\" <$> TF.attribute",
                    "name": "region",
                    "method": "region",
                    "conflicts": [],
                    "type": "TF.Attr s P.Text",
                    "class": "HasRegion",
                    "optional": false,
                    "label": "_region"
                },
                {
                    "default": "TF.Nil",
                    "computed": false,
                    "required": false,
                    "help": [],
                    "forceNew": true,
                    "encoder": "TF.assign \"space\" <$> TF.attribute",
                    "name": "space",
                    "method": "space",
                    "conflicts": [],
                    "type": "TF.Attr s P.Text",
                    "class": "HasSpace",
                    "optional": true,
                    "label": "_space"
                }
            ],
            "schema": "Resource",
            "name": "AppResource",
            "attributes": [
                {
                    "default": "TF.Nil",
                    "computed": true,
                    "required": false,
                    "help": [],
                    "forceNew": false,
                    "encoder": "TF.assign \"all_config_vars\" <$> TF.attribute",
                    "name": "all_config_vars",
                    "method": "computedAllConfigVars",
                    "conflicts": [],
                    "type": "TF.Attr s (P.HashMap P.Text (TF.Attr s P.Text))",
                    "class": "HasComputedAllConfigVars",
                    "optional": false,
                    "label": "_computedAllConfigVars"
                },
                {
                    "default": "TF.Nil",
                    "computed": true,
                    "required": false,
                    "help": [],
                    "forceNew": false,
                    "encoder": "TF.assign \"config_vars\" <$> TF.attribute",
                    "name": "config_vars",
                    "method": "computedConfigVars",
                    "conflicts": [],
                    "type": "TF.Attr s [TF.Attr s (P.HashMap P.Text (TF.Attr s P.Text))]",
                    "class": "HasComputedConfigVars",
                    "optional": true,
                    "label": "_computedConfigVars"
                },
                {
                    "default": "TF.Nil",
                    "computed": true,
                    "required": false,
                    "help": [],
                    "forceNew": false,
                    "encoder": "TF.assign \"git_url\" <$> TF.attribute",
                    "name": "git_url",
                    "method": "computedGitUrl",
                    "conflicts": [],
                    "type": "TF.Attr s P.Text",
                    "class": "HasComputedGitUrl",
                    "optional": false,
                    "label": "_computedGitUrl"
                },
                {
                    "default": "TF.Nil",
                    "computed": true,
                    "required": false,
                    "help": [],
                    "forceNew": false,
                    "encoder": "TF.assign \"heroku_hostname\" <$> TF.attribute",
                    "name": "heroku_hostname",
                    "method": "computedHerokuHostname",
                    "conflicts": [],
                    "type": "TF.Attr s P.Text",
                    "class": "HasComputedHerokuHostname",
                    "optional": false,
                    "label": "_computedHerokuHostname"
                },
                {
                    "default": "TF.Nil",
                    "computed": true,
                    "required": false,
                    "help": [],
                    "forceNew": true,
                    "encoder": "TF.assign \"internal_routing\" <$> TF.attribute",
                    "name": "internal_routing",
                    "method": "computedInternalRouting",
                    "conflicts": [],
                    "type": "TF.Attr s P.Bool",
                    "class": "HasComputedInternalRouting",
                    "optional": true,
                    "label": "_computedInternalRouting"
                },
                {
                    "default": "TF.Nil",
                    "computed": true,
                    "required": false,
                    "help": [],
                    "forceNew": false,
                    "encoder": "TF.assign \"stack\" <$> TF.attribute",
                    "name": "stack",
                    "method": "computedStack",
                    "conflicts": [],
                    "type": "TF.Attr s P.Text",
                    "class": "HasComputedStack",
                    "optional": true,
                    "label": "_computedStack"
                },
                {
                    "default": "TF.Nil",
                    "computed": true,
                    "required": false,
                    "help": [],
                    "forceNew": false,
                    "encoder": "TF.assign \"web_url\" <$> TF.attribute",
                    "name": "web_url",
                    "method": "computedWebUrl",
                    "conflicts": [],
                    "type": "TF.Attr s P.Text",
                    "class": "HasComputedWebUrl",
                    "optional": false,
                    "label": "_computedWebUrl"
                }
            ],
            "parameters": [
                {
                    "default": "_name",
                    "computed": false,
                    "required": true,
                    "help": [],
                    "forceNew": false,
                    "encoder": "TF.assign \"name\" <$> TF.attribute",
                    "name": "name",
                    "method": "name",
                    "conflicts": [],
                    "type": "TF.Attr s P.Text",
                    "class": "HasName",
                    "optional": false,
                    "label": "_name"
                },
                {
                    "default": "_region",
                    "computed": false,
                    "required": true,
                    "help": [],
                    "forceNew": true,
                    "encoder": "TF.assign \"region\" <$> TF.attribute",
                    "name": "region",
                    "method": "region",
                    "conflicts": [],
                    "type": "TF.Attr s P.Text",
                    "class": "HasRegion",
                    "optional": false,
                    "label": "_region"
                }
            ],
            "type": "AppResource s",
            "original": "heroku_app"
        },
        {
            "arguments": [
                {
                    "default": "_app",
                    "computed": false,
                    "required": true,
                    "help": [],
                    "forceNew": true,
                    "encoder": "TF.assign \"app\" <$> TF.attribute",
                    "name": "app",
                    "method": "app",
                    "conflicts": [],
                    "type": "TF.Attr s P.Text",
                    "class": "HasApp",
                    "optional": false,
                    "label": "_app"
                },
                {
                    "default": "TF.value P.True",
                    "computed": false,
                    "required": false,
                    "help": [],
                    "forceNew": false,
                    "encoder": "TF.assign \"enabled\" <$> TF.attribute",
                    "name": "enabled",
                    "method": "enabled",
                    "conflicts": [],
                    "type": "TF.Attr s P.Bool",
                    "class": "HasEnabled",
                    "optional": true,
                    "label": "_enabled"
                },
                {
                    "default": "_name",
                    "computed": false,
                    "required": true,
                    "help": [],
                    "forceNew": true,
                    "encoder": "TF.assign \"name\" <$> TF.attribute",
                    "name": "name",
                    "method": "name",
                    "conflicts": [],
                    "type": "TF.Attr s P.Text",
                    "class": "HasName",
                    "optional": false,
                    "label": "_name"
                }
            ],
            "schema": "Resource",
            "name": "AppFeatureResource",
            "attributes": [],
            "parameters": [
                {
                    "default": "_app",
                    "computed": false,
                    "required": true,
                    "help": [],
                    "forceNew": true,
                    "encoder": "TF.assign \"app\" <$> TF.attribute",
                    "name": "app",
                    "method": "app",
                    "conflicts": [],
                    "type": "TF.Attr s P.Text",
                    "class": "HasApp",
                    "optional": false,
                    "label": "_app"
                },
                {
                    "default": "_name",
                    "computed": false,
                    "required": true,
                    "help": [],
                    "forceNew": true,
                    "encoder": "TF.assign \"name\" <$> TF.attribute",
                    "name": "name",
                    "method": "name",
                    "conflicts": [],
                    "type": "TF.Attr s P.Text",
                    "class": "HasName",
                    "optional": false,
                    "label": "_name"
                }
            ],
            "type": "AppFeatureResource s",
            "original": "heroku_app_feature"
        },
        {
            "arguments": [
                {
                    "default": "_app",
                    "computed": false,
                    "required": true,
                    "help": [],
                    "forceNew": true,
                    "encoder": "TF.assign \"app\" <$> TF.attribute",
                    "name": "app",
                    "method": "app",
                    "conflicts": [],
                    "type": "TF.Attr s P.Text",
                    "class": "HasApp",
                    "optional": false,
                    "label": "_app"
                },
                {
                    "default": "_slugId",
                    "computed": false,
                    "required": true,
                    "help": [],
                    "forceNew": true,
                    "encoder": "TF.assign \"slug_id\" <$> TF.attribute",
                    "name": "slug_id",
                    "method": "slugId",
                    "conflicts": [],
                    "type": "TF.Attr s P.Text",
                    "class": "HasSlugId",
                    "optional": false,
                    "label": "_slugId"
                }
            ],
            "schema": "Resource",
            "name": "AppReleaseResource",
            "attributes": [
                {
                    "default": "TF.Nil",
                    "computed": true,
                    "required": false,
                    "help": [],
                    "forceNew": false,
                    "encoder": "TF.assign \"description\" <$> TF.attribute",
                    "name": "description",
                    "method": "computedDescription",
                    "conflicts": [],
                    "type": "TF.Attr s P.Text",
                    "class": "HasComputedDescription",
                    "optional": true,
                    "label": "_computedDescription"
                }
            ],
            "parameters": [
                {
                    "default": "_app",
                    "computed": false,
                    "required": true,
                    "help": [],
                    "forceNew": true,
                    "encoder": "TF.assign \"app\" <$> TF.attribute",
                    "name": "app",
                    "method": "app",
                    "conflicts": [],
                    "type": "TF.Attr s P.Text",
                    "class": "HasApp",
                    "optional": false,
                    "label": "_app"
                },
                {
                    "default": "_slugId",
                    "computed": false,
                    "required": true,
                    "help": [],
                    "forceNew": true,
                    "encoder": "TF.assign \"slug_id\" <$> TF.attribute",
                    "name": "slug_id",
                    "method": "slugId",
                    "conflicts": [],
                    "type": "TF.Attr s P.Text",
                    "class": "HasSlugId",
                    "optional": false,
                    "label": "_slugId"
                }
            ],
            "type": "AppReleaseResource s",
            "original": "heroku_app_release"
        },
        {
            "arguments": [
                {
                    "default": "_app",
                    "computed": false,
                    "required": true,
                    "help": [],
                    "forceNew": true,
                    "encoder": "TF.assign \"app\" <$> TF.attribute",
                    "name": "app",
                    "method": "app",
                    "conflicts": [],
                    "type": "TF.Attr s P.Text",
                    "class": "HasApp",
                    "optional": false,
                    "label": "_app"
                },
                {
                    "default": "_certificateChain",
                    "computed": false,
                    "required": true,
                    "help": [],
                    "forceNew": false,
                    "encoder": "TF.assign \"certificate_chain\" <$> TF.attribute",
                    "name": "certificate_chain",
                    "method": "certificateChain",
                    "conflicts": [],
                    "type": "TF.Attr s P.Text",
                    "class": "HasCertificateChain",
                    "optional": false,
                    "label": "_certificateChain"
                },
                {
                    "default": "_privateKey",
                    "computed": false,
                    "required": true,
                    "help": [],
                    "forceNew": false,
                    "encoder": "TF.assign \"private_key\" <$> TF.attribute",
                    "name": "private_key",
                    "method": "privateKey",
                    "conflicts": [],
                    "type": "TF.Attr s P.Text",
                    "class": "HasPrivateKey",
                    "optional": false,
                    "label": "_privateKey"
                }
            ],
            "schema": "Resource",
            "name": "CertResource",
            "attributes": [
                {
                    "default": "TF.Nil",
                    "computed": true,
                    "required": false,
                    "help": [],
                    "forceNew": false,
                    "encoder": "TF.assign \"cname\" <$> TF.attribute",
                    "name": "cname",
                    "method": "computedCname",
                    "conflicts": [],
                    "type": "TF.Attr s P.Text",
                    "class": "HasComputedCname",
                    "optional": false,
                    "label": "_computedCname"
                },
                {
                    "default": "TF.Nil",
                    "computed": true,
                    "required": false,
                    "help": [],
                    "forceNew": false,
                    "encoder": "TF.assign \"name\" <$> TF.attribute",
                    "name": "name",
                    "method": "computedName",
                    "conflicts": [],
                    "type": "TF.Attr s P.Text",
                    "class": "HasComputedName",
                    "optional": false,
                    "label": "_computedName"
                }
            ],
            "parameters": [
                {
                    "default": "_app",
                    "computed": false,
                    "required": true,
                    "help": [],
                    "forceNew": true,
                    "encoder": "TF.assign \"app\" <$> TF.attribute",
                    "name": "app",
                    "method": "app",
                    "conflicts": [],
                    "type": "TF.Attr s P.Text",
                    "class": "HasApp",
                    "optional": false,
                    "label": "_app"
                },
                {
                    "default": "_certificateChain",
                    "computed": false,
                    "required": true,
                    "help": [],
                    "forceNew": false,
                    "encoder": "TF.assign \"certificate_chain\" <$> TF.attribute",
                    "name": "certificate_chain",
                    "method": "certificateChain",
                    "conflicts": [],
                    "type": "TF.Attr s P.Text",
                    "class": "HasCertificateChain",
                    "optional": false,
                    "label": "_certificateChain"
                },
                {
                    "default": "_privateKey",
                    "computed": false,
                    "required": true,
                    "help": [],
                    "forceNew": false,
                    "encoder": "TF.assign \"private_key\" <$> TF.attribute",
                    "name": "private_key",
                    "method": "privateKey",
                    "conflicts": [],
                    "type": "TF.Attr s P.Text",
                    "class": "HasPrivateKey",
                    "optional": false,
                    "label": "_privateKey"
                }
            ],
            "type": "CertResource s",
            "original": "heroku_cert"
        },
        {
            "arguments": [
                {
                    "default": "_app",
                    "computed": false,
                    "required": true,
                    "help": [],
                    "forceNew": true,
                    "encoder": "TF.assign \"app\" <$> TF.attribute",
                    "name": "app",
                    "method": "app",
                    "conflicts": [],
                    "type": "TF.Attr s P.Text",
                    "class": "HasApp",
                    "optional": false,
                    "label": "_app"
                },
                {
                    "default": "_hostname",
                    "computed": false,
                    "required": true,
                    "help": [],
                    "forceNew": true,
                    "encoder": "TF.assign \"hostname\" <$> TF.attribute",
                    "name": "hostname",
                    "method": "hostname",
                    "conflicts": [],
                    "type": "TF.Attr s P.Text",
                    "class": "HasHostname",
                    "optional": false,
                    "label": "_hostname"
                }
            ],
            "schema": "Resource",
            "name": "DomainResource",
            "attributes": [
                {
                    "default": "TF.Nil",
                    "computed": true,
                    "required": false,
                    "help": [],
                    "forceNew": false,
                    "encoder": "TF.assign \"cname\" <$> TF.attribute",
                    "name": "cname",
                    "method": "computedCname",
                    "conflicts": [],
                    "type": "TF.Attr s P.Text",
                    "class": "HasComputedCname",
                    "optional": false,
                    "label": "_computedCname"
                }
            ],
            "parameters": [
                {
                    "default": "_app",
                    "computed": false,
                    "required": true,
                    "help": [],
                    "forceNew": true,
                    "encoder": "TF.assign \"app\" <$> TF.attribute",
                    "name": "app",
                    "method": "app",
                    "conflicts": [],
                    "type": "TF.Attr s P.Text",
                    "class": "HasApp",
                    "optional": false,
                    "label": "_app"
                },
                {
                    "default": "_hostname",
                    "computed": false,
                    "required": true,
                    "help": [],
                    "forceNew": true,
                    "encoder": "TF.assign \"hostname\" <$> TF.attribute",
                    "name": "hostname",
                    "method": "hostname",
                    "conflicts": [],
                    "type": "TF.Attr s P.Text",
                    "class": "HasHostname",
                    "optional": false,
                    "label": "_hostname"
                }
            ],
            "type": "DomainResource s",
            "original": "heroku_domain"
        },
        {
            "arguments": [
                {
                    "default": "_app",
                    "computed": false,
                    "required": true,
                    "help": [],
                    "forceNew": true,
                    "encoder": "TF.assign \"app\" <$> TF.attribute",
                    "name": "app",
                    "method": "app",
                    "conflicts": [],
                    "type": "TF.Attr s P.Text",
                    "class": "HasApp",
                    "optional": false,
                    "label": "_app"
                },
                {
                    "default": "_url",
                    "computed": false,
                    "required": true,
                    "help": [],
                    "forceNew": true,
                    "encoder": "TF.assign \"url\" <$> TF.attribute",
                    "name": "url",
                    "method": "url",
                    "conflicts": [],
                    "type": "TF.Attr s P.Text",
                    "class": "HasUrl",
                    "optional": false,
                    "label": "_url"
                }
            ],
            "schema": "Resource",
            "name": "DrainResource",
            "attributes": [
                {
                    "default": "TF.Nil",
                    "computed": true,
                    "required": false,
                    "help": [],
                    "forceNew": false,
                    "encoder": "TF.assign \"token\" <$> TF.attribute",
                    "name": "token",
                    "method": "computedToken",
                    "conflicts": [],
                    "type": "TF.Attr s P.Text",
                    "class": "HasComputedToken",
                    "optional": false,
                    "label": "_computedToken"
                }
            ],
            "parameters": [
                {
                    "default": "_app",
                    "computed": false,
                    "required": true,
                    "help": [],
                    "forceNew": true,
                    "encoder": "TF.assign \"app\" <$> TF.attribute",
                    "name": "app",
                    "method": "app",
                    "conflicts": [],
                    "type": "TF.Attr s P.Text",
                    "class": "HasApp",
                    "optional": false,
                    "label": "_app"
                },
                {
                    "default": "_url",
                    "computed": false,
                    "required": true,
                    "help": [],
                    "forceNew": true,
                    "encoder": "TF.assign \"url\" <$> TF.attribute",
                    "name": "url",
                    "method": "url",
                    "conflicts": [],
                    "type": "TF.Attr s P.Text",
                    "class": "HasUrl",
                    "optional": false,
                    "label": "_url"
                }
            ],
            "type": "DrainResource s",
            "original": "heroku_drain"
        },
        {
            "arguments": [
                {
                    "default": "_app",
                    "computed": false,
                    "required": true,
                    "help": [],
                    "forceNew": true,
                    "encoder": "TF.assign \"app\" <$> TF.attribute",
                    "name": "app",
                    "method": "app",
                    "conflicts": [],
                    "type": "TF.Attr s P.Text",
                    "class": "HasApp",
                    "optional": false,
                    "label": "_app"
                },
                {
                    "default": "_quantity",
                    "computed": false,
                    "required": true,
                    "help": [],
                    "forceNew": false,
                    "encoder": "TF.assign \"quantity\" <$> TF.attribute",
                    "name": "quantity",
                    "method": "quantity",
                    "conflicts": [],
                    "type": "TF.Attr s P.Integer",
                    "class": "HasQuantity",
                    "optional": false,
                    "label": "_quantity"
                },
                {
                    "default": "_size",
                    "computed": false,
                    "required": true,
                    "help": [],
                    "forceNew": false,
                    "encoder": "TF.assign \"size\" <$> TF.attribute",
                    "name": "size",
                    "method": "size",
                    "conflicts": [],
                    "type": "TF.Attr s P.Text",
                    "class": "HasSize",
                    "optional": false,
                    "label": "_size"
                },
                {
                    "default": "_type'",
                    "computed": false,
                    "required": true,
                    "help": [],
                    "forceNew": false,
                    "encoder": "TF.assign \"type\" <$> TF.attribute",
                    "name": "type",
                    "method": "type'",
                    "conflicts": [],
                    "type": "TF.Attr s P.Text",
                    "class": "HasType'",
                    "optional": false,
                    "label": "_type'"
                }
            ],
            "schema": "Resource",
            "name": "FormationResource",
            "attributes": [],
            "parameters": [
                {
                    "default": "_app",
                    "computed": false,
                    "required": true,
                    "help": [],
                    "forceNew": true,
                    "encoder": "TF.assign \"app\" <$> TF.attribute",
                    "name": "app",
                    "method": "app",
                    "conflicts": [],
                    "type": "TF.Attr s P.Text",
                    "class": "HasApp",
                    "optional": false,
                    "label": "_app"
                },
                {
                    "default": "_quantity",
                    "computed": false,
                    "required": true,
                    "help": [],
                    "forceNew": false,
                    "encoder": "TF.assign \"quantity\" <$> TF.attribute",
                    "name": "quantity",
                    "method": "quantity",
                    "conflicts": [],
                    "type": "TF.Attr s P.Integer",
                    "class": "HasQuantity",
                    "optional": false,
                    "label": "_quantity"
                },
                {
                    "default": "_size",
                    "computed": false,
                    "required": true,
                    "help": [],
                    "forceNew": false,
                    "encoder": "TF.assign \"size\" <$> TF.attribute",
                    "name": "size",
                    "method": "size",
                    "conflicts": [],
                    "type": "TF.Attr s P.Text",
                    "class": "HasSize",
                    "optional": false,
                    "label": "_size"
                },
                {
                    "default": "_type'",
                    "computed": false,
                    "required": true,
                    "help": [],
                    "forceNew": false,
                    "encoder": "TF.assign \"type\" <$> TF.attribute",
                    "name": "type",
                    "method": "type'",
                    "conflicts": [],
                    "type": "TF.Attr s P.Text",
                    "class": "HasType'",
                    "optional": false,
                    "label": "_type'"
                }
            ],
            "type": "FormationResource s",
            "original": "heroku_formation"
        },
        {
            "arguments": [
                {
                    "default": "_name",
                    "computed": false,
                    "required": true,
                    "help": [],
                    "forceNew": false,
                    "encoder": "TF.assign \"name\" <$> TF.attribute",
                    "name": "name",
                    "method": "name",
                    "conflicts": [],
                    "type": "TF.Attr s P.Text",
                    "class": "HasName",
                    "optional": false,
                    "label": "_name"
                }
            ],
            "schema": "Resource",
            "name": "PipelineResource",
            "attributes": [],
            "parameters": [
                {
                    "default": "_name",
                    "computed": false,
                    "required": true,
                    "help": [],
                    "forceNew": false,
                    "encoder": "TF.assign \"name\" <$> TF.attribute",
                    "name": "name",
                    "method": "name",
                    "conflicts": [],
                    "type": "TF.Attr s P.Text",
                    "class": "HasName",
                    "optional": false,
                    "label": "_name"
                }
            ],
            "type": "PipelineResource s",
            "original": "heroku_pipeline"
        },
        {
            "arguments": [
                {
                    "default": "_app",
                    "computed": false,
                    "required": true,
                    "help": [],
                    "forceNew": true,
                    "encoder": "TF.assign \"app\" <$> TF.attribute",
                    "name": "app",
                    "method": "app",
                    "conflicts": [],
                    "type": "TF.Attr s P.Text",
                    "class": "HasApp",
                    "optional": false,
                    "label": "_app"
                },
                {
                    "default": "_pipeline",
                    "computed": false,
                    "required": true,
                    "help": [],
                    "forceNew": true,
                    "encoder": "TF.assign \"pipeline\" <$> TF.attribute",
                    "name": "pipeline",
                    "method": "pipeline",
                    "conflicts": [],
                    "type": "TF.Attr s P.Text",
                    "class": "HasPipeline",
                    "optional": false,
                    "label": "_pipeline"
                },
                {
                    "default": "_stage",
                    "computed": false,
                    "required": true,
                    "help": [],
                    "forceNew": true,
                    "encoder": "TF.assign \"stage\" <$> TF.attribute",
                    "name": "stage",
                    "method": "stage",
                    "conflicts": [],
                    "type": "TF.Attr s P.Text",
                    "class": "HasStage",
                    "optional": false,
                    "label": "_stage"
                }
            ],
            "schema": "Resource",
            "name": "PipelineCouplingResource",
            "attributes": [
                {
                    "default": "TF.Nil",
                    "computed": true,
                    "required": false,
                    "help": [],
                    "forceNew": false,
                    "encoder": "TF.assign \"app_id\" <$> TF.attribute",
                    "name": "app_id",
                    "method": "computedAppId",
                    "conflicts": [],
                    "type": "TF.Attr s P.Text",
                    "class": "HasComputedAppId",
                    "optional": false,
                    "label": "_computedAppId"
                }
            ],
            "parameters": [
                {
                    "default": "_app",
                    "computed": false,
                    "required": true,
                    "help": [],
                    "forceNew": true,
                    "encoder": "TF.assign \"app\" <$> TF.attribute",
                    "name": "app",
                    "method": "app",
                    "conflicts": [],
                    "type": "TF.Attr s P.Text",
                    "class": "HasApp",
                    "optional": false,
                    "label": "_app"
                },
                {
                    "default": "_pipeline",
                    "computed": false,
                    "required": true,
                    "help": [],
                    "forceNew": true,
                    "encoder": "TF.assign \"pipeline\" <$> TF.attribute",
                    "name": "pipeline",
                    "method": "pipeline",
                    "conflicts": [],
                    "type": "TF.Attr s P.Text",
                    "class": "HasPipeline",
                    "optional": false,
                    "label": "_pipeline"
                },
                {
                    "default": "_stage",
                    "computed": false,
                    "required": true,
                    "help": [],
                    "forceNew": true,
                    "encoder": "TF.assign \"stage\" <$> TF.attribute",
                    "name": "stage",
                    "method": "stage",
                    "conflicts": [],
                    "type": "TF.Attr s P.Text",
                    "class": "HasStage",
                    "optional": false,
                    "label": "_stage"
                }
            ],
            "type": "PipelineCouplingResource s",
            "original": "heroku_pipeline_coupling"
        },
        {
            "arguments": [
                {
                    "default": "_name",
                    "computed": false,
                    "required": true,
                    "help": [],
                    "forceNew": false,
                    "encoder": "TF.assign \"name\" <$> TF.attribute",
                    "name": "name",
                    "method": "name",
                    "conflicts": [],
                    "type": "TF.Attr s P.Text",
                    "class": "HasName",
                    "optional": false,
                    "label": "_name"
                },
                {
                    "default": "_organization",
                    "computed": false,
                    "required": true,
                    "help": [],
                    "forceNew": true,
                    "encoder": "TF.assign \"organization\" <$> TF.attribute",
                    "name": "organization",
                    "method": "organization",
                    "conflicts": [],
                    "type": "TF.Attr s P.Text",
                    "class": "HasOrganization",
                    "optional": false,
                    "label": "_organization"
                },
                {
                    "default": "TF.Nil",
                    "computed": false,
                    "required": false,
                    "help": [],
                    "forceNew": true,
                    "encoder": "TF.assign \"region\" <$> TF.attribute",
                    "name": "region",
                    "method": "region",
                    "conflicts": [],
                    "type": "TF.Attr s P.Text",
                    "class": "HasRegion",
                    "optional": true,
                    "label": "_region"
                },
                {
                    "default": "TF.value P.False",
                    "computed": false,
                    "required": false,
                    "help": [],
                    "forceNew": true,
                    "encoder": "TF.assign \"shield\" <$> TF.attribute",
                    "name": "shield",
                    "method": "shield",
                    "conflicts": [],
                    "type": "TF.Attr s P.Bool",
                    "class": "HasShield",
                    "optional": true,
                    "label": "_shield"
                }
            ],
            "schema": "Resource",
            "name": "SpaceResource",
            "attributes": [
                {
                    "default": "TF.Nil",
                    "computed": true,
                    "required": false,
                    "help": [],
                    "forceNew": false,
                    "encoder": "TF.assign \"outbound_ips\" <$> TF.attribute",
                    "name": "outbound_ips",
                    "method": "computedOutboundIps",
                    "conflicts": [],
                    "type": "TF.Attr s [TF.Attr s P.Text]",
                    "class": "HasComputedOutboundIps",
                    "optional": false,
                    "label": "_computedOutboundIps"
                },
                {
                    "default": "TF.Nil",
                    "computed": true,
                    "required": false,
                    "help": [],
                    "forceNew": false,
                    "encoder": "TF.assign \"trusted_ip_ranges\" <$> TF.attribute",
                    "name": "trusted_ip_ranges",
                    "method": "computedTrustedIpRanges",
                    "conflicts": [],
                    "type": "TF.Attr s [TF.Attr s (TF.Attr s P.Text)]",
                    "class": "HasComputedTrustedIpRanges",
                    "optional": true,
                    "label": "_computedTrustedIpRanges"
                }
            ],
            "parameters": [
                {
                    "default": "_name",
                    "computed": false,
                    "required": true,
                    "help": [],
                    "forceNew": false,
                    "encoder": "TF.assign \"name\" <$> TF.attribute",
                    "name": "name",
                    "method": "name",
                    "conflicts": [],
                    "type": "TF.Attr s P.Text",
                    "class": "HasName",
                    "optional": false,
                    "label": "_name"
                },
                {
                    "default": "_organization",
                    "computed": false,
                    "required": true,
                    "help": [],
                    "forceNew": true,
                    "encoder": "TF.assign \"organization\" <$> TF.attribute",
                    "name": "organization",
                    "method": "organization",
                    "conflicts": [],
                    "type": "TF.Attr s P.Text",
                    "class": "HasOrganization",
                    "optional": false,
                    "label": "_organization"
                }
            ],
            "type": "SpaceResource s",
            "original": "heroku_space"
        },
        {
            "arguments": [
                {
                    "default": "_email",
                    "computed": false,
                    "required": true,
                    "help": [],
                    "forceNew": true,
                    "encoder": "TF.assign \"email\" <$> TF.attribute",
                    "name": "email",
                    "method": "email",
                    "conflicts": [],
                    "type": "TF.Attr s P.Text",
                    "class": "HasEmail",
                    "optional": false,
                    "label": "_email"
                },
                {
                    "default": "_permissions",
                    "computed": false,
                    "required": true,
                    "help": [],
                    "forceNew": false,
                    "encoder": "TF.assign \"permissions\" <$> TF.attribute",
                    "name": "permissions",
                    "method": "permissions",
                    "conflicts": [],
                    "type": "TF.Attr s [TF.Attr s (TF.Attr s P.Text)]",
                    "class": "HasPermissions",
                    "optional": false,
                    "label": "_permissions"
                },
                {
                    "default": "_space",
                    "computed": false,
                    "required": true,
                    "help": [],
                    "forceNew": true,
                    "encoder": "TF.assign \"space\" <$> TF.attribute",
                    "name": "space",
                    "method": "space",
                    "conflicts": [],
                    "type": "TF.Attr s P.Text",
                    "class": "HasSpace",
                    "optional": false,
                    "label": "_space"
                }
            ],
            "schema": "Resource",
            "name": "SpaceAppAccessResource",
            "attributes": [],
            "parameters": [
                {
                    "default": "_email",
                    "computed": false,
                    "required": true,
                    "help": [],
                    "forceNew": true,
                    "encoder": "TF.assign \"email\" <$> TF.attribute",
                    "name": "email",
                    "method": "email",
                    "conflicts": [],
                    "type": "TF.Attr s P.Text",
                    "class": "HasEmail",
                    "optional": false,
                    "label": "_email"
                },
                {
                    "default": "_permissions",
                    "computed": false,
                    "required": true,
                    "help": [],
                    "forceNew": false,
                    "encoder": "TF.assign \"permissions\" <$> TF.attribute",
                    "name": "permissions",
                    "method": "permissions",
                    "conflicts": [],
                    "type": "TF.Attr s [TF.Attr s (TF.Attr s P.Text)]",
                    "class": "HasPermissions",
                    "optional": false,
                    "label": "_permissions"
                },
                {
                    "default": "_space",
                    "computed": false,
                    "required": true,
                    "help": [],
                    "forceNew": true,
                    "encoder": "TF.assign \"space\" <$> TF.attribute",
                    "name": "space",
                    "method": "space",
                    "conflicts": [],
                    "type": "TF.Attr s P.Text",
                    "class": "HasSpace",
                    "optional": false,
                    "label": "_space"
                }
            ],
            "type": "SpaceAppAccessResource s",
            "original": "heroku_space_app_access"
        },
        {
            "arguments": [
                {
                    "default": "_rule",
                    "computed": false,
                    "required": true,
                    "help": [],
                    "forceNew": false,
                    "encoder": "TF.assign \"rule\" <$> TF.attribute",
                    "name": "rule",
                    "method": "rule",
                    "conflicts": [],
                    "type": "TF.Attr s (P.NonEmpty (TF.Attr s (Rule s)))",
                    "class": "HasRule",
                    "optional": false,
                    "label": "_rule"
                },
                {
                    "default": "_space",
                    "computed": false,
                    "required": true,
                    "help": [],
                    "forceNew": true,
                    "encoder": "TF.assign \"space\" <$> TF.attribute",
                    "name": "space",
                    "method": "space",
                    "conflicts": [],
                    "type": "TF.Attr s P.Text",
                    "class": "HasSpace",
                    "optional": false,
                    "label": "_space"
                }
            ],
            "schema": "Resource",
            "name": "SpaceInboundRulesetResource",
            "attributes": [],
            "parameters": [
                {
                    "default": "_rule",
                    "computed": false,
                    "required": true,
                    "help": [],
                    "forceNew": false,
                    "encoder": "TF.assign \"rule\" <$> TF.attribute",
                    "name": "rule",
                    "method": "rule",
                    "conflicts": [],
                    "type": "TF.Attr s (P.NonEmpty (TF.Attr s (Rule s)))",
                    "class": "HasRule",
                    "optional": false,
                    "label": "_rule"
                },
                {
                    "default": "_space",
                    "computed": false,
                    "required": true,
                    "help": [],
                    "forceNew": true,
                    "encoder": "TF.assign \"space\" <$> TF.attribute",
                    "name": "space",
                    "method": "space",
                    "conflicts": [],
                    "type": "TF.Attr s P.Text",
                    "class": "HasSpace",
                    "optional": false,
                    "label": "_space"
                }
            ],
            "type": "SpaceInboundRulesetResource s",
            "original": "heroku_space_inbound_ruleset"
        },
        {
            "arguments": [
                {
                    "default": "_space",
                    "computed": false,
                    "required": true,
                    "help": [],
                    "forceNew": true,
                    "encoder": "TF.assign \"space\" <$> TF.attribute",
                    "name": "space",
                    "method": "space",
                    "conflicts": [],
                    "type": "TF.Attr s P.Text",
                    "class": "HasSpace",
                    "optional": false,
                    "label": "_space"
                },
                {
                    "default": "_vpcPeeringConnectionId",
                    "computed": false,
                    "required": true,
                    "help": [],
                    "forceNew": true,
                    "encoder": "TF.assign \"vpc_peering_connection_id\" <$> TF.attribute",
                    "name": "vpc_peering_connection_id",
                    "method": "vpcPeeringConnectionId",
                    "conflicts": [],
                    "type": "TF.Attr s P.Text",
                    "class": "HasVpcPeeringConnectionId",
                    "optional": false,
                    "label": "_vpcPeeringConnectionId"
                }
            ],
            "schema": "Resource",
            "name": "SpacePeeringConnectionAccepterResource",
            "attributes": [
                {
                    "default": "TF.Nil",
                    "computed": true,
                    "required": false,
                    "help": [],
                    "forceNew": false,
                    "encoder": "TF.assign \"status\" <$> TF.attribute",
                    "name": "status",
                    "method": "computedStatus",
                    "conflicts": [],
                    "type": "TF.Attr s P.Text",
                    "class": "HasComputedStatus",
                    "optional": false,
                    "label": "_computedStatus"
                },
                {
                    "default": "TF.Nil",
                    "computed": true,
                    "required": false,
                    "help": [],
                    "forceNew": false,
                    "encoder": "TF.assign \"type\" <$> TF.attribute",
                    "name": "type",
                    "method": "computedType'",
                    "conflicts": [],
                    "type": "TF.Attr s P.Text",
                    "class": "HasComputedType'",
                    "optional": false,
                    "label": "_computedType'"
                }
            ],
            "parameters": [
                {
                    "default": "_space",
                    "computed": false,
                    "required": true,
                    "help": [],
                    "forceNew": true,
                    "encoder": "TF.assign \"space\" <$> TF.attribute",
                    "name": "space",
                    "method": "space",
                    "conflicts": [],
                    "type": "TF.Attr s P.Text",
                    "class": "HasSpace",
                    "optional": false,
                    "label": "_space"
                },
                {
                    "default": "_vpcPeeringConnectionId",
                    "computed": false,
                    "required": true,
                    "help": [],
                    "forceNew": true,
                    "encoder": "TF.assign \"vpc_peering_connection_id\" <$> TF.attribute",
                    "name": "vpc_peering_connection_id",
                    "method": "vpcPeeringConnectionId",
                    "conflicts": [],
                    "type": "TF.Attr s P.Text",
                    "class": "HasVpcPeeringConnectionId",
                    "optional": false,
                    "label": "_vpcPeeringConnectionId"
                }
            ],
            "type": "SpacePeeringConnectionAccepterResource s",
            "original": "heroku_space_peering_connection_accepter"
        },
        {
            "arguments": [
                {
                    "default": "_name",
                    "computed": false,
                    "required": true,
                    "help": [],
                    "forceNew": true,
                    "encoder": "TF.assign \"name\" <$> TF.attribute",
                    "name": "name",
                    "method": "name",
                    "conflicts": [],
                    "type": "TF.Attr s P.Text",
                    "class": "HasName",
                    "optional": false,
                    "label": "_name"
                },
                {
                    "default": "_publicIp",
                    "computed": false,
                    "required": true,
                    "help": [],
                    "forceNew": true,
                    "encoder": "TF.assign \"public_ip\" <$> TF.attribute",
                    "name": "public_ip",
                    "method": "publicIp",
                    "conflicts": [],
                    "type": "TF.Attr s P.Text",
                    "class": "HasPublicIp",
                    "optional": false,
                    "label": "_publicIp"
                },
                {
                    "default": "_routableCidrs",
                    "computed": false,
                    "required": true,
                    "help": [],
                    "forceNew": true,
                    "encoder": "TF.assign \"routable_cidrs\" <$> TF.attribute",
                    "name": "routable_cidrs",
                    "method": "routableCidrs",
                    "conflicts": [],
                    "type": "TF.Attr s [TF.Attr s (TF.Attr s P.Text)]",
                    "class": "HasRoutableCidrs",
                    "optional": false,
                    "label": "_routableCidrs"
                },
                {
                    "default": "_space",
                    "computed": false,
                    "required": true,
                    "help": [],
                    "forceNew": true,
                    "encoder": "TF.assign \"space\" <$> TF.attribute",
                    "name": "space",
                    "method": "space",
                    "conflicts": [],
                    "type": "TF.Attr s P.Text",
                    "class": "HasSpace",
                    "optional": false,
                    "label": "_space"
                }
            ],
            "schema": "Resource",
            "name": "SpaceVpnConnectionResource",
            "attributes": [
                {
                    "default": "TF.Nil",
                    "computed": true,
                    "required": false,
                    "help": [],
                    "forceNew": false,
                    "encoder": "TF.assign \"ike_version\" <$> TF.attribute",
                    "name": "ike_version",
                    "method": "computedIkeVersion",
                    "conflicts": [],
                    "type": "TF.Attr s P.Integer",
                    "class": "HasComputedIkeVersion",
                    "optional": false,
                    "label": "_computedIkeVersion"
                },
                {
                    "default": "TF.Nil",
                    "computed": true,
                    "required": false,
                    "help": [],
                    "forceNew": false,
                    "encoder": "TF.assign \"space_cidr_block\" <$> TF.attribute",
                    "name": "space_cidr_block",
                    "method": "computedSpaceCidrBlock",
                    "conflicts": [],
                    "type": "TF.Attr s P.Text",
                    "class": "HasComputedSpaceCidrBlock",
                    "optional": false,
                    "label": "_computedSpaceCidrBlock"
                },
                {
                    "default": "TF.Nil",
                    "computed": true,
                    "required": false,
                    "help": [],
                    "forceNew": false,
                    "encoder": "TF.assign \"tunnels\" <$> TF.attribute",
                    "name": "tunnels",
                    "method": "computedTunnels",
                    "conflicts": [],
                    "type": "TF.Attr s [Tunnels s]",
                    "class": "HasComputedTunnels",
                    "optional": true,
                    "label": "_computedTunnels"
                }
            ],
            "parameters": [
                {
                    "default": "_name",
                    "computed": false,
                    "required": true,
                    "help": [],
                    "forceNew": true,
                    "encoder": "TF.assign \"name\" <$> TF.attribute",
                    "name": "name",
                    "method": "name",
                    "conflicts": [],
                    "type": "TF.Attr s P.Text",
                    "class": "HasName",
                    "optional": false,
                    "label": "_name"
                },
                {
                    "default": "_publicIp",
                    "computed": false,
                    "required": true,
                    "help": [],
                    "forceNew": true,
                    "encoder": "TF.assign \"public_ip\" <$> TF.attribute",
                    "name": "public_ip",
                    "method": "publicIp",
                    "conflicts": [],
                    "type": "TF.Attr s P.Text",
                    "class": "HasPublicIp",
                    "optional": false,
                    "label": "_publicIp"
                },
                {
                    "default": "_routableCidrs",
                    "computed": false,
                    "required": true,
                    "help": [],
                    "forceNew": true,
                    "encoder": "TF.assign \"routable_cidrs\" <$> TF.attribute",
                    "name": "routable_cidrs",
                    "method": "routableCidrs",
                    "conflicts": [],
                    "type": "TF.Attr s [TF.Attr s (TF.Attr s P.Text)]",
                    "class": "HasRoutableCidrs",
                    "optional": false,
                    "label": "_routableCidrs"
                },
                {
                    "default": "_space",
                    "computed": false,
                    "required": true,
                    "help": [],
                    "forceNew": true,
                    "encoder": "TF.assign \"space\" <$> TF.attribute",
                    "name": "space",
                    "method": "space",
                    "conflicts": [],
                    "type": "TF.Attr s P.Text",
                    "class": "HasSpace",
                    "optional": false,
                    "label": "_space"
                }
            ],
            "type": "SpaceVpnConnectionResource s",
            "original": "heroku_space_vpn_connection"
        },
        {
            "arguments": [
                {
                    "default": "_app",
                    "computed": false,
                    "required": true,
                    "help": [],
                    "forceNew": true,
                    "encoder": "TF.assign \"app\" <$> TF.attribute",
                    "name": "app",
                    "method": "app",
                    "conflicts": [],
                    "type": "TF.Attr s P.Text",
                    "class": "HasApp",
                    "optional": false,
                    "label": "_app"
                },
                {
                    "default": "_email",
                    "computed": false,
                    "required": true,
                    "help": [],
                    "forceNew": true,
                    "encoder": "TF.assign \"email\" <$> TF.attribute",
                    "name": "email",
                    "method": "email",
                    "conflicts": [],
                    "type": "TF.Attr s P.Text",
                    "class": "HasEmail",
                    "optional": false,
                    "label": "_email"
                },
                {
                    "default": "_permissions",
                    "computed": false,
                    "required": true,
                    "help": [],
                    "forceNew": false,
                    "encoder": "TF.assign \"permissions\" <$> TF.attribute",
                    "name": "permissions",
                    "method": "permissions",
                    "conflicts": [],
                    "type": "TF.Attr s (P.NonEmpty (TF.Attr s (TF.Attr s P.Text)))",
                    "class": "HasPermissions",
                    "optional": false,
                    "label": "_permissions"
                }
            ],
            "schema": "Resource",
            "name": "TeamCollaboratorResource",
            "attributes": [],
            "parameters": [
                {
                    "default": "_app",
                    "computed": false,
                    "required": true,
                    "help": [],
                    "forceNew": true,
                    "encoder": "TF.assign \"app\" <$> TF.attribute",
                    "name": "app",
                    "method": "app",
                    "conflicts": [],
                    "type": "TF.Attr s P.Text",
                    "class": "HasApp",
                    "optional": false,
                    "label": "_app"
                },
                {
                    "default": "_email",
                    "computed": false,
                    "required": true,
                    "help": [],
                    "forceNew": true,
                    "encoder": "TF.assign \"email\" <$> TF.attribute",
                    "name": "email",
                    "method": "email",
                    "conflicts": [],
                    "type": "TF.Attr s P.Text",
                    "class": "HasEmail",
                    "optional": false,
                    "label": "_email"
                },
                {
                    "default": "_permissions",
                    "computed": false,
                    "required": true,
                    "help": [],
                    "forceNew": false,
                    "encoder": "TF.assign \"permissions\" <$> TF.attribute",
                    "name": "permissions",
                    "method": "permissions",
                    "conflicts": [],
                    "type": "TF.Attr s (P.NonEmpty (TF.Attr s (TF.Attr s P.Text)))",
                    "class": "HasPermissions",
                    "optional": false,
                    "label": "_permissions"
                }
            ],
            "type": "TeamCollaboratorResource s",
            "original": "heroku_team_collaborator"
        }
    ],
    "dependencies": [
        "base",
        "unordered-containers",
        "text",
        "terrafomo",
        "hashable",
        "microlens"
    ],
    "name": "Heroku",
    "parameters": [],
    "package": "terrafomo-heroku",
    "type": "Provider",
    "original": "heroku"
}